blupants/__init__.py
blupants/blupants_car.py
blupants/blupants_client.py
blupants/edumip.py
blupants/rc_balance_dstr.py
blupants/sonar.py
blupants-1.0.0a6.data/scripts/blupants
blupants-1.0.0a6.data/scripts/qrcode_wifi
blupants-1.0.0a6.dist-info/LICENSE
blupants-1.0.0a6.dist-info/METADATA
blupants-1.0.0a6.dist-info/WHEEL
blupants-1.0.0a6.dist-info/top_level.txt
blupants-1.0.0a6.dist-info/RECORD
