Metadata-Version: 2.1
Name: blupants
Version: 1.0.0a6
Summary: BluPants client module. This module allows your robot to execute commands from the BluPants Coding Lab (https://blupants.org).
Home-page: https://blupants.com
Author: BluPants
Author-email: blupants.robot@gmail.com
License: Apache-2.0
Platform: UNKNOWN
Requires-Python: >=3.4
Requires-Dist: Adafruit-BBIO
Requires-Dist: flask
Requires-Dist: flask-restful
Requires-Dist: pycrypto
Requires-Dist: pyctrl
Requires-Dist: rcpy
Requires-Dist: requests
